ovid/__init__.py
ovid/basic.py
ovid/inspecting.py
ovid/producing.py
ovid-0.6.0.dist-info/LICENSE
ovid-0.6.0.dist-info/METADATA
ovid-0.6.0.dist-info/WHEEL
ovid-0.6.0.dist-info/top_level.txt
ovid-0.6.0.dist-info/RECORD
