Metadata-Version: 2.1
Name: ovid
Version: 0.6.0
Summary: Text metamorphosis toolbox'
Home-page: https://github.com/veikman/ovid
Author: Viktor Eikman
Author-email: viktor.eikman@gmail.com
License: GPL-3.0-only
Platform: UNKNOWN
Classifier: Development Status :: 4 - Beta
Classifier: Intended Audience :: Developers
Classifier: License :: OSI Approved :: GNU General Public License v3 (GPLv3)
Classifier: Operating System :: OS Independent
Classifier: Programming Language :: Python :: 3
Classifier: Topic :: Database
Classifier: Topic :: Games/Entertainment :: Board Games
Classifier: Topic :: Games/Entertainment :: Multi-User Dungeons (MUD)
Classifier: Topic :: Games/Entertainment :: Role-Playing
Classifier: Topic :: Software Development :: Libraries :: Python Modules
Classifier: Topic :: Text Processing :: Filters
Classifier: Topic :: Text Processing :: Markup
Requires-Python: >=3.6
